{
  "date": "2026-07-11",
  "try": {
    "usd": 0.021257,
    "eur": 0.018615,
    "gbp": 0.015861,
    "chf": 0.017162,
    "jpy": 3.434066,
    "sar": 0.079838,
    "aed": 0.077992,
    "azn": 0.036137,
    "cad": 0.030116,
    "aud": 0.030559,
    "rub": 1.638807,
    "dkk": 0.139009,
    "sek": 0.205036,
    "nok": 0.207426,
    "kwd": 0.006575,
    "zar": 0.346765,
    "bhd": 0.008015,
    "cny": 0.144003,
    "krw": 31.847134,
    "ron": 0.097461,
    "pkr": 5.899705,
    "kzt": 10.090817,
    "qar": 0.077316,
    "gel": 0.056057,
    "byn": 0.060807,
    "uzs": 255.362615,
    "huf": 6.6357,
    "iqd": 27.86602
  }
}